jsonify_resume/__init__.py
jsonify_resume/main.py
prompt
schema.json
jsonify_resume-0.1.1.dist-info/LICENSE
jsonify_resume-0.1.1.dist-info/METADATA
jsonify_resume-0.1.1.dist-info/WHEEL
jsonify_resume-0.1.1.dist-info/entry_points.txt
jsonify_resume-0.1.1.dist-info/RECORD
