Metadata-Version: 2.1
Name: jsonify-resume
Version: 0.1.1
Summary: A cli that converts resumes into JSON Resume schema
License: MIT
Author: Ashish Binu
Author-email: ashishbinu90@gmail.com
Requires-Python: >=3.11,<4.0
Classifier: License :: OSI Approved :: MIT License
Classifier: Programming Language :: Python :: 3
Classifier: Programming Language :: Python :: 3.11
Requires-Dist: pdftotext (>=2.2.2,<3.0.0)
Requires-Dist: python-dotenv (>=1.0.0,<2.0.0)
Requires-Dist: python-magic (>=0.4.27,<0.5.0)
Requires-Dist: revchatgpt (>=6.8.6,<7.0.0)
Requires-Dist: rich (>=13.5.2,<14.0.0)
Requires-Dist: typer[all] (>=0.9.0,<0.10.0)
